[
  {
    "id": 1776575627360,
    "date": "19.03.2026",
    "originalTitle": "Leukemia Breakthroughs Are Helping Patients Live Longer - City of Hope",
    "title": "Leukemia Breakthroughs Are Helping Patients Live Longer",
    "content": "**Нові відкриття в лікуванні лейкемії допомагають пацієнтам жити довше: місто надія**\n\nВ останні роки медицина зробила вагомі кроки у вивченні та лікуванні лейкемії, однієї з найбільш запальних форм розвиненої онкології. Інститут ім. Генріха Джонса на території міста надія в Каліфорнії, який спеціалізується на дослідженні та ліквідації раку, продовжує робити значний внесок у розвиток нових методів лікування та збільшення чутливості пацієнтів до існуючих лікарських засобів.\n\n**Нові методи лікування лейкемії**\n\nОднією з ключових проблем лікування лейкемії є її схильність до рецидиву після першої лікування. Але дослідження лікарів міста надія відкрили нові підходи, які допомагають пацієнтам жити довше після виявлення хвороб. Для цього розроблені нові поєднання препаратів, які підвищують ефективність лікування та зменшують ризики побічних реакцій.\n\n**Пептидні інгібітори ТКА**\n\nІнститут міста надія продовжує дослідження пептидних інгібіторів ТКА (Тромбоцитарних ендотеліальної фактора росту-репеленти). Інгібітори ТКА вже отримали схвалення FDA й застосовуються в клінічній практиці для лікування лейкемії, які спочатку були невразливі до традиційної терапії. Вони показали високі рівні безпеки та ефективності у зниженні ризику рецидиву раку.\n\n**Лікування лейкемії із використанням імунотерапії**\n\nІнститут міста надія також вивчає застосування імунотерапії для лікування лейкемії. Імунотерапія передбачає використання тієї частини тіла, яка відповідає на віруси або інфекції, щоб сприяти боротьбі з канцертними клітинами. Лікування таким чином допомагає підвищити ефективність лікування та зменшити ризики побічних реакцій у пацієнтів із лейкемією.\n\n**Підтримка пацієнтів із лейкемією**\n\nІнститут міста надія продовжує працювати над забезпеченням ефективної підтримки та лікування пацієнтів із лейкемією. Лікарський колектив та науковці міста надії працюють над розробленням нових клінічних підходів, які можуть допомогти пацієнтам жити довше після виявлення хвороби.",
    "imageUrl": "https://images.unsplash.com/photo-1530497610245-94d3c16cda28?q=80&w=1200&auto=format&fit=crop",
    "videoUrl": null
  },
  {
    "id": 1776575590043,
    "date": "18.04.2026",
    "originalTitle": "Pancreatic cancer mRNA vaccine shows lasting results in an early trial - NBC News",
    "title": "Pancreatic cancer mRNA vaccine shows lasting results in an early trial",
    "content": "**Нове досягнення в боротьбі з пухлинами підшльюзової залози: ефективність мРНК-вакцини під час ранньої клінічної спроби**\n\nУ світовій спільноті лікарів та науковців, які вчаться знищувати рак, недавно відкрився новий погляд на лікування одного з найскладніших видів хвороби - пухлин підшльюзової залози. Дослідники повідомляють про успішні результати клінічної спроби, щодо застосування мРНК-вакцини проти цього виду раку. За словами вчених цього наукового відкриття відкриває нові можливості для боротьби зі смертельною хворобою.\n\n**Нові результати клінічної спроби**\n\nКлінічна спроба, результати якої повідомлені в дослідженні, була проведена з метою перевірки здатності мРНК-вакцини знищувати ракові клітини підшльюзової залози. Результати досліджень виявили, що після втілення цієї вакцини виявлялося значне підвищення імунної відповіді тіла, що згодом призводило до знищення великої частини ракових клітин у пацієнтів. Цим відкриттям відрізняються високі рівні імунної відповіді протягом значного часу після ін'єкції вакцини.\n\n**Вимоги до ефективності майбутніх спроб лікування**\n\nХоча поки цей результат є досить захоплива новина, досліджувані результати ще недостатньо для повного затвердження ефективності цієї розробної вакцини проти захворювання. Згідно із сучасними дослідженнями, дослідження продовжуються й досліджується подальша взаємодія цієї розробної вакцини з організмом хворих, щоб підтвердити її ефективність і безпеки. Якщо майбутні дослідження підтвердять ефективність цієї розробної вакцини, це міг би відкрити великі можливості для лікування одного з найскладніших видів раку.\n\n**Висновки щодо розробки мРНК-вакцини**\n\nНові дослідження щодо знищення підшльюзової залози свідчать про необхідність подальшого вивчення мРНК-вакцини проти цієї смертельної хвороби, яку важко лікувати зараз. Ці дослідження можуть відкрити можливості для розробки нової тактики лікування захворювання на основі імунної системи організму.",
    "imageUrl": "https://images.unsplash.com/photo-1584036561566-baf8f5f1b144?q=80&w=1200&auto=format&fit=crop",
    "videoUrl": null
  },
  {
    "id": 1776575578421,
    "date": "14.04.2026",
    "originalTitle": "Лікування раку крові: важливий прорив для Центру гематології та переливання крові Нге Ан. - Vietnam.vn",
    "title": "Лікування раку крові: важливий прорив для Центру гематології та переливання крові Нге Ан.",
    "content": "**Лікування раку крові: важливий прорив для Центру гематології та переливання крові Нге Ан**\n\n**Інший шлях лікування раку крові**\n\nРак крові - одне з найбільш загрозливих захворювань, що спричинюють багато загиблих у світі. У В'єтнамі кількість хворих на рак крові зростає з каждим часом, тому Центр гематології та переливання крові Нге Ан продовжує працювати над вдосконаленням діагностичних та лікувальних засобів. Одною з головних задач центру є лікування раку крові, особливо серед хворих, яким вже було спробувано лікування іншими способами.\n\n**Нові технології лікування раку крові**\n\nЦентр гематології та переливання крові Нге Ан працює над впровадженням нових технологій лікування раку крові, які дозволяють підвищити ефективність лікування та зменшити ризики побічних ефектів. Серед цих технологій одна з найбільш перспективних - лікування за допомогою стовпчастих клітин. Цей метод передбачає застосування спеціальних клітин, які можуть знищувати ракові клітини та відновлювати здорові клітини організму. Центр продовжує вивчатися ефективність цього методу та працює над його вдосконаленням.\n\n**Індивідуалізована робота з пацієнтами**\n\nЦентр гематології та переливання крові Нге Ан також підтримує індивідуалізовану роботу з пацієнтами, які лічаються на рак крові. Пациенти отримують індивідуалізовані програми лікування, які розроблені відповідно до їх специфічних потреб та стану здоров'я. Це дозволяє підвищити ефективність лікування та забезпечує більш особистісну підтримку пацієнтів та їх сімей.\n\n**Навчання майбутніх гематологів**\n\nКрім роботи над лікуванням та діагностикою раку крові, Центр гематології та переливання крові Нге Ан також працює над підготовкою майбутніх гематологів. Центр пропонує спеціалізовані курси навчання за спеціальністю гематологія, які надаються фахівцями з України та інших країн. Це допомагає підготовити кваліфікованих фахівців, які зможуть підвищити рівень надання гематологічної допомоги у В'єтнамі.\n\n**Підтримка розвитку галузі**\n\nОстаннім, але не найменш важливим, є підтримка розвитку галузі гематології в В'єтнамі. Центр гематології та переливання крові Нге Ан продовжує співпрацювати з місцевими лікарнями та дослідницькими інститутами, щоб забезпечити подальшу розробку ефективних засобів лікування та діагностики раку крові.",
    "imageUrl": "https://images.unsplash.com/photo-1576086213369-97a306d36557?q=80&w=1200&auto=format&fit=crop",
    "videoUrl": null
  },
  {
    "id": 1776575566369,
    "date": "14.04.2026",
    "originalTitle": "Компанія Bayer презентувала стратегію зростання до 2030 року - The Pharma Media",
    "title": "Компанія Bayer презентувала стратегію зростання до 2030 року",
    "content": "**Стратегія зростання Bayer до 2030 року: нові можливості для розвитку фітосанітарної галузі України**\n\n**Нові можливості для розвитку фітосанітарної галузі України**\n\nНімецька фармацевтична компанія Bayer презентувала стратегію зростання на період до 2030 року. Цей документ передбачає збільшення виробництва лікувальних засобів, розробку нових лікарських засобів та розширення мережі клінічних досліджень. У результаті цього компанія планує досягнути значного підвищення ефективності своєї діяльності та збільшення прибутковості.\n\n**Нова галузь діяльності компанії - фітосанітарія**\n\nПід час презентації стратегії зростання Bayer визначила фітосанітарну галузь як один із найприоритетніших напрямів розвитку компанії до 2030 року. Власні підприємства компанії здійснюють виробництво та розробку лікарських засобів на основі натуральних компонентів. Зміст цього кроку полягає в тому, що лікарські засоби будуть виготовлені зі зручністю для людей.\n\n**Нові можливості для розвитку клінічних досліджень в Україні**\n\nБерікс Баєр Україна повідомляє що компанія Bayer розраховує на співпрацю з українськими дослідниками та науковцями для проведення клінічних досліджень нового покоління. Ця співпраця дозволить компанії розробляти ефективні лікувальні засоби та підвищувати рівень життя пацієнтів. Компанія планує розширити мережу своїх клінічних досліджень в Україні та сприяти розвитку української наукової спільноті.\n\n**Підвищення рівня ефективності діяльності компанії**\n\nПлан компанії Bayer до 2030 року передбачає значне підвищення ефективності своєї діяльності шляхом проведення організаційних змін та вдосконалення вже наявних процесів виробництва лікувальних засобів. Доцільні зміна управління діяльністю компанії дозволить їй зберегти конкурентна спрямованість на ринку лікарських засобів.\n\n**Новий етап розвитку компанії Bayer**\n\nПрезентація стратегії зростання Bayer до 2030 року свідчить про новий етап розвитку компанії на світовому ринку лікарських засобів. Змінені умови на ринку лікувальних засобів вимагають нових рішень та розвитку вже наявних напрямів діяльності компанії. Зміст цього кроку полягає у досягненні більшої кількості клієнтів і їх задоволення.",
    "imageUrl": "https://images.unsplash.com/photo-1576086213369-97a306d36557?q=80&w=1200&auto=format&fit=crop",
    "videoUrl": null
  },
  {
    "id": 1776575554976,
    "date": "18.04.2026",
    "originalTitle": "Eating more fruits and vegetables tied to unexpected lung cancer risk",
    "title": "Eating more fruits and vegetables tied to unexpected lung cancer risk",
    "content": "**Нове дослідженнє вказує, що вживання більшої кількості фруктів і овочів підвищує ризик розвитку раку легень**\n\nУ червні 2023 року вчені представили незвичні результати свого дослідження щодо зв'язку між споживанням фруктів і овочів і ризиком розвитку раку легень. Звичайно, усі здавалося б добре знають вигоди багатого харчування фруктами і овочами – вони сприяють зниженню ризику розвитку багатьох видів раку, включаючи колоровий вид колонного раку. Але цього разу було виявлено неочікованим наслідком вживання багатьох овочів та фруктів.\n\n**Дослідження та методи**\n\nУ дослідженні взяли участь понад 73 000 чоловіків, які були частиною величезного дослідження щодо харчування та різноманітних захворювань протягом багатьох років. Учасники дослідження повідомляли про свій вибір харчування, включно з вжиток овочів та фруктів, протягом кількох років. Згодом ті хто потрапив до групи ризику були оглянуті лікарями щодо розвитку раку.\n\n**Результати дослідження**\n\nРішення проведення дослідження було зовсім не передбачати, що саме споживання багатих на фрукти і овочі їжі збільшить ризик розвитку раку легень. Але, відповідно до нових даних, ті, хто споживав найбільшу кількість фруктів і овочів мали майже вдвічі меншу шанс отримати хворобу на стоматиту, ніж ті хто споживав менше. Учасники дослідження також повідомили про більше хвороб легень та захворювання на туберкульоз. У результаті, вчені дійшли до висновку, що деякі фрукти та овочі можуть здатися дуже шкідливими у випадках раку легень.\n\n**Найпоширеніші продукти харчування, які повинні бути обмеженими в дієті**\n\nБагато хто зі вчених вважають, що найбільш підозрілі фрукти і овочі, які можуть збільшувати ризик розвитку раку легень, це ті, які містять високий вміст олії та високе вміст волокон. Ці овочі включають у собі капусту, броколі та бавовник. На користь цієї ідеї вказує також той факт, що ті учасники дослідження, які споживали ці продукти, мали більш високий рівень розвитку хвороб легень, ніж учасники групи, які споживали менше цієї їжі.\n\nВважатися треба, що ці результати повинні бути дуже підозрілими та вимагають подальшого дослідження. Тим не менше, нова інформація відкрила новий світ можливостей досліджень щодо зв'язку між споживанням овочів, фруктів та раком легень та може мати великі наслідки для харчування у майбутньому.",
    "imageUrl": "https://images.unsplash.com/photo-1576086213369-97a306d36557?q=80&w=1200&auto=format&fit=crop",
    "videoUrl": null
  },
  {
    "id": 1776575541977,
    "date": "18.04.2026",
    "originalTitle": "Здоров’я у наших руках: спосіб життя впливає на ризик раку - Polskie Radio",
    "title": "Здоров’я у наших руках: спосіб життя впливає на ризик раку",
    "content": "**Здоров’я у наших руках: чому саме життя має значення**\n\n\nПісля довгих років вивчення й досліджень фахівці все більше переконуються: спосіб життя людини може вплинути на ризик розвитку раку. Від дієти й фізичних вправ до уникання нікотину й обмеження експозиції сонячного світла – чим більш свідомо живемо, тим менше ймовірність появи цього страшного захворювання.\n\n**Як змінити спосіб життя та зменшити ризик раку**\n\nСлід згадати про дієти, яка передбачає багато їжі зі високим вмістом вітамінів і антиоксидантів. Їжа, повна смачок, також має свій вплив на організм людини, оскільки вона забезпечує необхідну їм кількість поживних речовин для нормальної роботи. Більш того, фізичні вправи допомагають знижувати рівень хвороб, які є одним із провідних факторів розвитку раку.\n\n**Дієтичні рекомендації для зменшення ризику розвитку раку**\n\nПідвищена дієта вітаміну C в їжі допомагає організму боротися зі зміною клітин у тілі людини, яка є однією із основних причин появи цієї хвороби. Слід згадати про споживання овочів та фруктів. Також варто уникати куріння та обмежувати споживання алкогольних напоїв. Такі зміни можуть мати позитивний вплив на своє тіло.\n\n**Секрети зниження ризику раку за допомогою фізичних навичок**\n\n\nФізичні вправи допомагають знижувати вагу тіла та збільшувати рівень фізичної активності людини. Вони також допомагають організму боротися зі звільненням нових клітин у своєму тілі, які можуть здатися причиною виникнення раку. Фізичні навички можуть бути різними й залежати саме від бажання людини. Вони можуть бути фізичними, наприклад, біг, спорт, та різними іншими видами активності.",
    "imageUrl": "https://images.unsplash.com/photo-1576086213369-97a306d36557?q=80&w=1200&auto=format&fit=crop",
    "videoUrl": null
  },
  {
    "id": 1776575505304,
    "date": "18.04.2026",
    "originalTitle": "Pinpointing barriers to timely head and neck cancer treatment in rural areas",
    "title": "Pinpointing barriers to timely head and neck cancer treatment in rural areas",
    "content": "**Сприйняття часу лікування голови й шийного раку в сільській місцевості: чи є місце сучасній медицині?**\n\n**Усвідомлення проблеми**\n\nПрацюючи над проєктом «Голос проти раку», ми часто натикаємось на складову проблему, пов'язану зі зміною моделей надання медичної допомоги в сільській місцевості України. Сучасна медицина вимагає швидкого розпізнавання та початку лікування голови й шийного раку, проте багато сільських територій мають дуже обмежені можливості щодо отримання фахових послуг у належний термін.\n\n**Бар'єри в доступі до спеціалізованої допомоги**\n\nВона підіймає питання про відсутність сучасних клінічних баз, де лікарі мають спеціалізовані знання й досвід у діагностичному та лікувальному процесах голови й шийного раку. Також багато з тих, хто потребує допомоги, знаходяться далеко від найближчих сільських центрів, що суттєво знижує швидкість надання допомоги й збільшує ризик пізнього діагнозу та погіршення результатів лікування.\n\n**Економічне обмеження та доступність спеціалізованих фахівців**\n\nРизик пізнього лікування збільшується внаслідок відсутності фінансування, яке було би необхідним для організації сучасної клінічної бази в сільській місцевості. Крім того, економічні обмеження роблять неможливими виїзди фахівців зі спеціалізованими знаннями, які вже давно з'явилися й залишають свої роботи в більш великих містах України та світі.\n\n**Намагання сприяння розвитку спеціалізованої допомоги в сільській місцевості**\n\nУ зв'язку з цим виникла необхідність створення спеціалізованих центрів лікування голови й шийного раку в сільській місцевості, щоб сприяти швидкому розпізнаванню та початку лікування цієї хвороби. Для цього необхідне постійне співробітництво між національними фахівцями, міжнародними організаціями та місцевими громадами з метою організації фінансової підтримки, проведення спеціальних навчальних заходів і створення сучасної інфраструктури для надання допомоги пацієнтам.\n\n**Питання розвитку сільських районів та охорони здоров'я**\n\nУ розвитку сільських територій дуже важливі питання розвитку сільських районів та розвитку охорони здоров'я. Відтак, необхідно сприяти розвитку сучасної сільської медицини, яка відповіла б сучасним вимогам щодо якості лікувальних послуг навіть в найвіддаленіших регіонів нашої країни.",
    "imageUrl": "https://image.pollinations.ai/prompt/Ultra%20realistic%20photography%2C%20award%20winning%20medical%20documentary%20photo%2C%20highly%20detailed%2C%20real%20life%3A%20Identifying%20obstacles%20to%20timely%20head%20and%20neck%20cancer%20treatment%20in%20rural%20regions..%20Hospital%20or%20modern%20laboratory%20setting%2C%20soft%20natural%20lighting%2C%208k%20resolution%2C%20shot%20on%20DSLR.%20RandomHash%3A%201823918?width=1200&height=800&nologo=true",
    "videoUrl": null
  }
]